utilspggmdatalab/__init__.py
utilspggmdatalab/utilspggmdatalab.py
utilspggmdatalab-0.4.dist-info/METADATA
utilspggmdatalab-0.4.dist-info/WHEEL
utilspggmdatalab-0.4.dist-info/top_level.txt
utilspggmdatalab-0.4.dist-info/RECORD
